RotiNat/RotiNat.py
RotiNat/__init__.py
RotiNat-0.0.3.dist-info/License.txt
RotiNat-0.0.3.dist-info/METADATA
RotiNat-0.0.3.dist-info/WHEEL
RotiNat-0.0.3.dist-info/top_level.txt
RotiNat-0.0.3.dist-info/RECORD
