Metadata-Version: 2.1
Name: RotiNat
Version: 0.0.3
Summary: A package to calculate ROTI (Rate of TEC Index)
Home-page: https://github.com/Tesfay-Tesfu/ROT_ROTI
Author: Tesfay Tesfu
Author-email: tesfayphysics@gmail.com
License: MIT
Platform: UNKNOWN
Classifier: Programming Language :: Python :: 3
Classifier: License :: OSI Approved :: MIT License
Classifier: Operating System :: OS Independent
Requires-Python: >=3.6
License-File: License.txt
Requires-Dist: pandas
Requires-Dist: numpy
Requires-Dist: ipywidgets
